examples/ArgumentParameters.xircuits
examples/CompulsoryPorts.xircuits
examples/ControlflowExample.xircuits
examples/DynamicPorts.xircuits
examples/HelloXircuits.xircuits
examples/ParallelSimulations.xircuits
examples/SettingVariables.xircuits
examples/TVB.xircuits
examples/XircuitsContext.xircuits
examples/__init__.py
tvbextxircuits/__init__.py
tvbextxircuits/_version.py
tvbextxircuits/hatch_build_hook.py
tvbextxircuits/nb_generator.py
tvbextxircuits/settings_loader.py
tvbextxircuits/start_xircuits.py
tvbextxircuits/utils.py
tvbextxircuits/.xircuits/.gitmodules
tvbextxircuits/.xircuits/config.ini
tvbextxircuits/compiler/__init__.py
tvbextxircuits/compiler/compiler.py
tvbextxircuits/compiler/generator.py
tvbextxircuits/compiler/node.py
tvbextxircuits/compiler/parser.py
tvbextxircuits/compiler/port.py
tvbextxircuits/compiler/vendor/LICENSE
tvbextxircuits/compiler/vendor/__init__.py
tvbextxircuits/compiler/vendor/unparse.py
tvbextxircuits/handlers/__init__.py
tvbextxircuits/handlers/compile_xircuits.py
tvbextxircuits/handlers/component_parser.py
tvbextxircuits/handlers/components.py
tvbextxircuits/handlers/config.py
tvbextxircuits/handlers/debugger.py
tvbextxircuits/handlers/json_parser.py
tvbextxircuits/handlers/request_folder.py
tvbextxircuits/handlers/request_library.py
tvbextxircuits/handlers/request_submodule.py
tvbextxircuits/handlers/user_config.py
tvbextxircuits/hpc_config/__init__.py
tvbextxircuits/hpc_config/parse_files.py
tvbextxircuits/hpc_config/pyunicore_config.py
tvbextxircuits/labextension/build_log.json
tvbextxircuits/labextension/package.json
tvbextxircuits/labextension/schemas/tvb-ext-xircuits/package.json.orig
tvbextxircuits/labextension/schemas/tvb-ext-xircuits/settings.json
tvbextxircuits/labextension/static/55df9a4a8c8bd49ce490.gif
tvbextxircuits/labextension/static/lib_index_js.02e5cb3f185caeb02764.js
tvbextxircuits/labextension/static/lib_index_js.02e5cb3f185caeb02764.js.map
tvb_ext_xircuits-2.1.3.dist-info/METADATA
tvb_ext_xircuits-2.1.3.dist-info/WHEEL
tvb_ext_xircuits-2.1.3.dist-info/entry_points.txt
tvb_ext_xircuits-2.1.3.dist-info/licenses/LICENSE
tvb_ext_xircuits-2.1.3.dist-info/RECORD
