Metadata-Version: 2.4
Name: tvb-ext-xircuits
Version: 2.1.3
Dynamic: Keywords
Summary: Jupyterlab extension for building TVB workflows in a visual and interactive manner
Project-URL: Homepage, https://github.com/the-virtual-brain/tvb-ext-xircuits
Project-URL: Bug Tracker, https://req.thevirtualbrain.org
Project-URL: Repository, https://github.com/the-virtual-brain/tvb-ext-xircuits
Author-email: TVB-Xircuits Team <science@codemart.ro>
License:                                  Apache License
License-File: LICENSE
Classifier: Framework :: Jupyter
Classifier: Framework :: Jupyter :: JupyterLab
Classifier: Framework :: Jupyter :: JupyterLab :: 4
Classifier: Framework :: Jupyter :: JupyterLab :: Extensions
Classifier: Framework :: Jupyter :: JupyterLab :: Extensions :: Prebuilt
Classifier: License :: OSI Approved :: Apache Software License
Classifier: Programming Language :: Python
Classifier: Programming Language :: Python :: 3
Classifier: Programming Language :: Python :: 3.9
Classifier: Programming Language :: Python :: 3.10
Classifier: Programming Language :: Python :: 3.11
Classifier: Programming Language :: Python :: 3.12
Classifier: Programming Language :: Python :: 3.13
Requires-Python: >=3.9
Requires-Dist: asgiref
Requires-Dist: dill
Requires-Dist: docutils
Requires-Dist: importlib-resources
Requires-Dist: ipykernel
Requires-Dist: jupyter-core
Requires-Dist: jupyter-server<3,>=2.0.1
Requires-Dist: jupyterlab-server
Requires-Dist: jupyterlab-widgets
Requires-Dist: jupyterlab>=4.0.0
Requires-Dist: nbformat
Requires-Dist: notebook-shim
Requires-Dist: numpy
Requires-Dist: packaging
Requires-Dist: pyunicore
Requires-Dist: requests
Requires-Dist: toml
Requires-Dist: tornado
Requires-Dist: tvb-ext-bucket
Requires-Dist: tvb-ext-unicore
Requires-Dist: tvb-library
Provides-Extra: full
Requires-Dist: siibra; extra == 'full'
Requires-Dist: tvb-framework; extra == 'full'
Requires-Dist: tvb-gdist; extra == 'full'
Requires-Dist: tvb-widgets>=1.0; extra == 'full'
Provides-Extra: test
Requires-Dist: coverage; extra == 'test'
Requires-Dist: pytest; extra == 'test'
Requires-Dist: pytest-asyncio; extra == 'test'
Requires-Dist: pytest-cov; extra == 'test'
Requires-Dist: pytest-jupyter[server]>=0.6.0; extra == 'test'
